MANIFEST.in
README
README.md
setup.cfg
setup.py
bibcure/__init__.py
bibcure/arxiv.py
bibcure/database.py
bibcure/doi.py
bibcure/in_db.py
bibcure/out_db.py
bibcure/title.py
bibcure.egg-info/PKG-INFO
bibcure.egg-info/SOURCES.txt
bibcure.egg-info/dependency_links.txt
bibcure.egg-info/requires.txt
bibcure.egg-info/top_level.txt
bibcure/bin/bibcure
bibcure/data/db_abbrev.json