Metadata-Version: 1.1
Name: bibcure
Version: 0.2.6
Summary:  Helps you to have a better bibtex file
Home-page: https://github.com/bibcure/bibcure
Author: Bruno Messias
Author-email: messias.physics@gmail.com
License: AGPLv3
Download-URL: https://github.com/bibcure/bibcure/archive/0.2.6.tar.gz
Keywords: bibtex,arxiv,doi,abbreviate,science,scientific-journals
Platform: UNKNOWN
Classifier: License :: OSI Approved :: GNU Affero General Public License v3 or later (AGPLv3+)
Classifier: Intended Audience :: Science/Research
Classifier: Programming Language :: Python
Classifier: Topic :: Text Processing :: Markup :: LaTeX
